protai/VERSION
protai/__init__.py
protai/auth.py
protai/ismarkdown.py
protai/mygroq.py
protai/protai.py
protai/texteffects.py
protai-1.1.1.data/data/requirements.txt
protai-1.1.1.dist-info/licenses/LICENSE
protai-1.1.1.dist-info/METADATA
protai-1.1.1.dist-info/WHEEL
protai-1.1.1.dist-info/entry_points.txt
protai-1.1.1.dist-info/top_level.txt
protai-1.1.1.dist-info/RECORD
