Metadata-Version: 2.4
Name: protai
Version: 1.1.1
Summary: A useful 0-Shot AI in the terminal
Home-page: https://github.com/protik09/terminal-ai
Author: Protik Banerji
Author-email: protik09@users.noreply.github.com
License: MIT
Classifier: Programming Language :: Python
Classifier: Programming Language :: Python :: 3
Classifier: Programming Language :: Python :: 3.10
Classifier: Programming Language :: Python :: Implementation :: CPython
Classifier: Topic :: Scientific/Engineering :: Artificial Intelligence
Requires-Python: >=3.10.0
License-File: LICENSE
Requires-Dist: setuptools
Requires-Dist: wheel
Requires-Dist: rich
Requires-Dist: keyring
Requires-Dist: prompt-toolkit
Requires-Dist: requests
Requires-Dist: orjson
Requires-Dist: tiktoken
Dynamic: author
Dynamic: author-email
Dynamic: classifier
Dynamic: description
Dynamic: description-content-type
Dynamic: home-page
Dynamic: license
Dynamic: license-file
Dynamic: requires-dist
Dynamic: requires-python
Dynamic: summary
